django_multitenant_saas-0.1.0.dist-info/licenses/LICENSE
multitenant/__init__.py
multitenant/managers.py
multitenant/middleware.py
multitenant/models.py
multitenant/utils.py
django_multitenant_saas-0.1.0.dist-info/METADATA
django_multitenant_saas-0.1.0.dist-info/WHEEL
django_multitenant_saas-0.1.0.dist-info/top_level.txt
django_multitenant_saas-0.1.0.dist-info/RECORD
