Metadata-Version: 2.4
Name: django-multitenant-saas
Version: 0.1.0
Summary: A plug-and-play multi-tenancy package for Django SaaS applications.
Author: Pranav Dixit
Author-email: pranavdixit20@gmail.com
License: MIT
Classifier: Framework :: Django
Classifier: Programming Language :: Python :: 3
Classifier: License :: OSI Approved :: MIT License
Classifier: Operating System :: OS Independent
License-File: LICENSE
Requires-Dist: Django>=3.2
Dynamic: author
Dynamic: author-email
Dynamic: classifier
Dynamic: description
Dynamic: description-content-type
Dynamic: license
Dynamic: license-file
Dynamic: requires-dist
Dynamic: summary
